{
  "exchange": {
    "j": "DCE",
    "eg": "DCE",
    "lg": "DCE",
    "cs": "DCE",
    "SF": "CZCE",
    "rr": "DCE",
    "sc": "INE",
    "OI": "CZCE",
    "PX": "CZCE",
    "SH": "CZCE",
    "ZC": "CZCE",
    "v": "DCE",
    "TA": "CZCE",
    "pp": "DCE",
    "lc": "GFEX",
    "nr": "INE",
    "CY": "CZCE",
    "m": "DCE",
    "bu": "SHFE",
    "rb": "SHFE",
    "sp": "SHFE",
    "p": "DCE",
    "l": "DCE",
    "pg": "DCE",
    "ps": "GFEX",
    "ec": "INE",
    "pb": "SHFE",
    "au": "SHFE",
    "wr": "SHFE",
    "FG": "CZCE",
    "PK": "CZCE",
    "PL": "CZCE",
    "hc": "SHFE",
    "IH": "CFFEX",
    "jd": "DCE",
    "ad": "SHFE",
    "TS": "CFFEX",
    "fb": "DCE",
    "bz": "DCE",
    "SA": "CZCE",
    "SR": "CZCE",
    "jm": "DCE",
    "si": "GFEX",
    "PM": "CZCE",
    "eb": "DCE",
    "lu": "INE",
    "ni": "SHFE",
    "ao": "SHFE",
    "RS": "CZCE",
    "br": "SHFE",
    "cu": "SHFE",
    "bb": "DCE",
    "zn": "SHFE",
    "c": "DCE",
    "op": "SHFE",
    "i": "DCE",
    "sn": "SHFE",
    "ss": "SHFE",
    "pd": "GFEX",
    "UR": "CZCE",
    "al": "SHFE",
    "pt": "GFEX",
    "ag": "SHFE",
    "y": "DCE",
    "a": "DCE",
    "AP": "CZCE",
    "pp2607F": "DCE",
    "CF": "CZCE",
    "MA": "CZCE",
    "PR": "CZCE",
    "IM": "CFFEX",
    "RI": "CZCE",
    "fu": "SHFE",
    "bc": "INE",
    "lh": "DCE",
    "v2611F": "DCE",
    "b": "DCE",
    "ru": "SHFE",
    "JR": "CZCE",
    "l2607F": "DCE",
    "l2612F": "DCE",
    "RM": "CZCE",
    "SM": "CZCE",
    "pp2608F": "DCE",
    "v2608F": "DCE",
    "TF": "CFFEX",
    "PF": "CZCE",
    "IC": "CFFEX",
    "v2612F": "DCE",
    "WH": "CZCE",
    "CJ": "CZCE",
    "v2609F": "DCE",
    "l2609F": "DCE",
    "IF": "CFFEX",
    "TL": "CFFEX",
    "pp2612F": "DCE",
    "T": "CFFEX",
    "v2610F": "DCE",
    "l2611F": "DCE",
    "l2610F": "DCE",
    "pp2610F": "DCE",
    "pp2609F": "DCE",
    "pp2611F": "DCE",
    "v2607F": "DCE",
    "l2608F": "DCE"
  },
  "name": {},
  "updated_at": "2026-06-26T21:38:16.687410"
}